pmr_elirobots_sdk/__init__.py
pmr_elirobots_sdk/_baseec.py
pmr_elirobots_sdk/_ec.py
pmr_elirobots_sdk/_info.py
pmr_elirobots_sdk/_kinematics.py
pmr_elirobots_sdk/_monitor.py
pmr_elirobots_sdk/_move.py
pmr_elirobots_sdk/_moveml.py
pmr_elirobots_sdk/_movett.py
pmr_elirobots_sdk/_profinet.py
pmr_elirobots_sdk/_servo.py
pmr_elirobots_sdk/_var.py
pmr_elirobots_sdk/types.py
pmr_elirobots_sdk-0.0.1.dist-info/METADATA
pmr_elirobots_sdk-0.0.1.dist-info/WHEEL
pmr_elirobots_sdk-0.0.1.dist-info/licenses/LICENSE
pmr_elirobots_sdk-0.0.1.dist-info/RECORD
